{"cameraMode":{"drawMode":0,"name":"Shaded","section":"Shading Mode"},"sceneLighting":true,"audioPlay":false,"sceneViewState":{"showFog":true,"showMaterialUpdate":false,"showSkybox":true,"showFlares":true,"showImageEffects":true,"showParticleSystems":true},"in2DMode":false,"pivot":{"x":3.2749996185302736,"y":5.833000183105469,"z":-0.16499996185302735},"rotation":{"x":-0.03935009986162186,"y":-0.9438052177429199,"z":0.3047301173210144,"w":-0.12184568494558335},"size":6.189516544342041,"orthographic":false}